pubmed_client.pyi
pubmed_client/__init__.py
pubmed_client/__init__.pyi
pubmed_client/pubmed_client.cpython-313-darwin.so
pubmed_client/py.typed
pubmed_client_py-0.0.2.dist-info/METADATA
pubmed_client_py-0.0.2.dist-info/WHEEL
pubmed_client_py-0.0.2.dist-info/RECORD
