Metadata-Version: 2.4
Name: pubmed-client-py
Version: 0.0.2
Classifier: Development Status :: 3 - Alpha
Classifier: Intended Audience :: Science/Research
Classifier: Intended Audience :: Developers
Classifier: License :: OSI Approved :: MIT License
Classifier: Programming Language :: Python :: 3
Classifier: Programming Language :: Python :: 3.12
Classifier: Programming Language :: Python :: 3.13
Classifier: Programming Language :: Rust
Classifier: Topic :: Scientific/Engineering :: Bio-Informatics
Classifier: Topic :: Software Development :: Libraries :: Python Modules
Summary: Python bindings for PubMed and PMC APIs for retrieving biomedical research articles
Keywords: pubmed,pmc,biomedical,research,api,bioinformatics
Author: illumination-k
License: MIT
Requires-Python: >=3.12
Project-URL: Homepage, https://github.com/illumination-k/pubmed-client-rs
Project-URL: Repository, https://github.com/illumination-k/pubmed-client-rs
Project-URL: Documentation, https://github.com/illumination-k/pubmed-client-rs/tree/main/pubmed-client-py
